dot/__init__.py
dot/__version__.py
dot/api.py
dot/cli.py
dot/config.py
dot/topic.py
dotfiler-0.0.2.dist-info/METADATA
dotfiler-0.0.2.dist-info/RECORD
dotfiler-0.0.2.dist-info/WHEEL
dotfiler-0.0.2.dist-info/entry_points.txt
dotfiler-0.0.2.dist-info/top_level.txt
